an_cudautility/__init__.py
an_cudautility/cudautility.py
an_cudautility-0.4.0.dist-info/LICENSE
an_cudautility-0.4.0.dist-info/METADATA
an_cudautility-0.4.0.dist-info/WHEEL
an_cudautility-0.4.0.dist-info/top_level.txt
an_cudautility-0.4.0.dist-info/RECORD
