Metadata-Version: 2.2
Name: an_cudautility
Version: 0.4.0
Summary: A package for an_cudautility.
Home-page: https://github.com/Atsushi888/Atsushi888
Author: Atsushi888
Author-email: Atsushi888 <vtgrotxu@gmail.com>
Project-URL: Homepage, https://github.com/Atsushi888/an_cudautility
Project-URL: Repository, https://github.com/Atsushi888/an_cudautility
Requires-Python: >=3.6
License-File: LICENSE
Dynamic: author
Dynamic: home-page
Dynamic: requires-python
